uv_demo/__init__.py
uv_demo/greetings.py
uv_demo-0.3.1.dist-info/WHEEL
uv_demo-0.3.1.dist-info/entry_points.txt
uv_demo-0.3.1.dist-info/METADATA
uv_demo-0.3.1.dist-info/RECORD
