Metadata-Version: 2.3
Name: uv-demo
Version: 0.3.1
Summary: Just a demo of the uv package manager for Python.
Author: Lucas Parzianello
Author-email: Lucas Parzianello <lucaspar@users.noreply.github.com>
License: MIT License
Classifier: Development Status :: 1 - Planning
Classifier: Intended Audience :: Developers
Classifier: License :: OSI Approved :: MIT License
Classifier: Operating System :: Unix
Classifier: Programming Language :: Python :: 3.11
Classifier: Programming Language :: Python :: 3.12
Classifier: Programming Language :: Python :: 3.13
Classifier: Programming Language :: Python :: 3.14
Classifier: Programming Language :: Python :: Implementation :: CPython
Classifier: Topic :: Terminals
Classifier: Typing :: Typed
Requires-Dist: loguru>=0.7.2
Requires-Python: >=3.11
Project-URL: Issues, https://github.com/lucaspar/uv-demo/issues
Project-URL: Releases, https://github.com/lucaspar/uv-demo/releases
Project-URL: Repository, https://github.com/lucaspar/uv-demo
